[
  {
    "name": "ui-002-page-transitions",
    "date": "ui-002-page-transitions",
    "summary": "",
    "tasks": {
      "done": 0,
      "total": 0
    },
    "artifacts": {
      "proposal": true,
      "tasks": true
    }
  },
  {
    "name": "ui-001-motion-system",
    "date": "ui-001-motion-system",
    "summary": "",
    "tasks": {
      "done": 0,
      "total": 0
    },
    "artifacts": {
      "proposal": true,
      "tasks": true
    }
  },
  {
    "name": "sys-005-seo-metadata",
    "date": "sys-005-seo-metadata",
    "summary": "",
    "tasks": {
      "done": 25,
      "total": 26
    },
    "artifacts": {
      "proposal": true,
      "tasks": true
    }
  },
  {
    "name": "sys-004-build-deployment-pipeline",
    "date": "sys-004-build-deployment-pipeline",
    "summary": "",
    "tasks": {
      "done": 13,
      "total": 13
    },
    "artifacts": {
      "proposal": true,
      "tasks": true
    }
  },
  {
    "name": "page-001-home-page",
    "date": "page-001-home-page",
    "summary": "Audit and validate the OptiFlow OS home page (`index.html`) against all capability specs. The home page already exists as the primary landing page with 13 content sections (Hero, Trust Bar, Problem, C",
    "tasks": {
      "done": 10,
      "total": 10
    },
    "artifacts": {
      "proposal": true,
      "tasks": true
    }
  },
  {
    "name": "ops-001",
    "date": "ops-001",
    "summary": "Implement the auto-discovery orchestration engine that routes OpenSpec commands through skills, agents, MCPs, hooks, and quality gates with full traceability from spec to production.",
    "tasks": {
      "done": 18,
      "total": 18
    },
    "artifacts": {
      "proposal": true,
      "tasks": true
    }
  },
  {
    "name": "design-system-core",
    "date": "design-system-core",
    "summary": "",
    "tasks": {
      "done": 9,
      "total": 9
    },
    "artifacts": {
      "proposal": true,
      "tasks": true
    }
  },
  {
    "name": "2026-07-04-image-optimization-pipeline",
    "date": "2026-07-04",
    "summary": "Add automated image optimization to the build pipeline — WebP/AVIF conversion via sharp, responsive `<picture>` elements, cache-control headers, and CSS utilities.",
    "tasks": {
      "done": 8,
      "total": 8
    },
    "artifacts": {
      "proposal": true,
      "tasks": true
    }
  },
  {
    "name": "2026-07-04-ui-005-cookie-consent-privacy-compliance",
    "date": "2026-07-04",
    "summary": "",
    "tasks": {
      "done": 28,
      "total": 28
    },
    "artifacts": {
      "proposal": true,
      "tasks": true
    }
  },
  {
    "name": "2026-07-03-id-ui-003-name-skeleton-loading-empty-st",
    "date": "2026-07-03",
    "summary": "Implement skeleton loading placeholders and empty state UIs across all pages to improve perceived performance and handle edge cases where content is unavailable.",
    "tasks": {
      "done": 8,
      "total": 8
    },
    "artifacts": {
      "proposal": true,
      "tasks": true
    }
  },
  {
    "name": "2026-07-01-api-001-form-processing-api",
    "date": "2026-07-01",
    "summary": "",
    "tasks": {
      "done": 22,
      "total": 22
    },
    "artifacts": {
      "proposal": true,
      "tasks": true
    }
  },
  {
    "name": "2026-07-01-api-002",
    "date": "2026-07-01",
    "summary": "Add admin authentication to protect the internal admin dashboard where OptiFlow team members can view form submissions and manage settings.",
    "tasks": {
      "done": 0,
      "total": 9
    },
    "artifacts": {
      "proposal": true,
      "tasks": true
    }
  },
  {
    "name": "2026-07-01-api-003-admin-dashboard",
    "date": "2026-07-01",
    "summary": "Fix CSS duplication, add submission persistence, and enhance the admin dashboard with stats, search, and detail view. Builds on api-002's auth layer.",
    "tasks": {
      "done": 17,
      "total": 17
    },
    "artifacts": {
      "proposal": true,
      "tasks": true
    }
  },
  {
    "name": "2026-07-01-api-004-email-notifications",
    "date": "2026-07-01",
    "summary": "",
    "tasks": {
      "done": 17,
      "total": 17
    },
    "artifacts": {
      "proposal": true,
      "tasks": true
    }
  },
  {
    "name": "2026-07-01-api-005-database-data-management",
    "date": "2026-07-01",
    "summary": "Define and implement a structured data management layer for the OptiFlow OS website's Cloudflare KV-backed application data. This capability covers data schemas, key structures, lifecycle policies, ad",
    "tasks": {
      "done": 0,
      "total": 26
    },
    "artifacts": {
      "proposal": true,
      "tasks": true
    }
  },
  {
    "name": "2026-07-01-api-006",
    "date": "2026-07-01",
    "summary": "Add comprehensive monitoring and observability to the OptiFlow OS Website, including a health check endpoint for uptime monitoring, enhanced admin dashboard with audit log viewer and email delivery st",
    "tasks": {
      "done": 21,
      "total": 21
    },
    "artifacts": {
      "proposal": true,
      "tasks": true
    }
  },
  {
    "name": "2026-07-01-lead-001-demo-booking",
    "date": "2026-07-01",
    "summary": "",
    "tasks": {
      "done": 24,
      "total": 24
    },
    "artifacts": {
      "proposal": true,
      "tasks": true
    }
  },
  {
    "name": "2026-07-01-lead-002",
    "date": "2026-07-01",
    "summary": "",
    "tasks": {
      "done": 27,
      "total": 27
    },
    "artifacts": {
      "proposal": true,
      "tasks": true
    }
  },
  {
    "name": "2026-07-01-legal-001",
    "date": "2026-07-01",
    "summary": "",
    "tasks": {
      "done": 23,
      "total": 23
    },
    "artifacts": {
      "proposal": true,
      "tasks": true
    }
  },
  {
    "name": "2026-07-01-ops-002-git-hooks-automation",
    "date": "2026-07-01",
    "summary": "",
    "tasks": {
      "done": 20,
      "total": 20
    },
    "artifacts": {
      "proposal": true,
      "tasks": true
    }
  },
  {
    "name": "2026-07-01-page-008-faq-self-service",
    "date": "2026-07-01",
    "summary": "",
    "tasks": {
      "done": 23,
      "total": 23
    },
    "artifacts": {
      "proposal": true,
      "tasks": true
    }
  },
  {
    "name": "2026-07-01-qa-001-accessibility-compliance",
    "date": "2026-07-01",
    "summary": "Comprehensive accessibility audit and remediation to ensure WCAG 2.2 Level AA compliance across all 14 public pages. Adds automated contrast testing to the validation pipeline, hardens existing a11y p",
    "tasks": {
      "done": 8,
      "total": 8
    },
    "artifacts": {
      "proposal": true,
      "tasks": true
    }
  },
  {
    "name": "2026-07-01-qa-002",
    "date": "2026-07-01",
    "summary": "Define and systematize the QA testing layer for the OptiFlow OS static marketing website. The testing suite covers all 12+ pages across 5 test dimensions: accessibility, SEO, navigation, responsive la",
    "tasks": {
      "done": 0,
      "total": 6
    },
    "artifacts": {
      "proposal": true,
      "tasks": true
    }
  },
  {
    "name": "2026-07-01-qa-003-code-quality-performance",
    "date": "2026-07-01",
    "summary": "",
    "tasks": {
      "done": 21,
      "total": 21
    },
    "artifacts": {
      "proposal": true,
      "tasks": true
    }
  },
  {
    "name": "2026-07-01-sys-005",
    "date": "2026-07-01",
    "summary": "Fix critical and high-priority SEO issues discovered during audit: absolute `og:image` URL for social sharing, duplicate skip links, LCP regression from lazy-loaded logo, hardcoded newsletter publish ",
    "tasks": {
      "done": 9,
      "total": 9
    },
    "artifacts": {
      "proposal": true,
      "tasks": true
    }
  },
  {
    "name": "2026-06-30-competitive-positioning",
    "date": "2026-06-30",
    "summary": "",
    "tasks": {
      "done": 0,
      "total": 17
    },
    "artifacts": {
      "proposal": true,
      "tasks": true
    }
  },
  {
    "name": "2026-06-30-interactive-runtime",
    "date": "2026-06-30",
    "summary": "",
    "tasks": {
      "done": 0,
      "total": 0
    },
    "artifacts": {
      "proposal": true,
      "tasks": true
    }
  },
  {
    "name": "2026-06-30-page-002",
    "date": "2026-06-30",
    "summary": "The Problem & Solutions page is a narrative-driven landing page that diagnoses the 6 biggest operational challenges Indian MSMEs face daily — from WhatsApp chaos to Excel version hell — and positions ",
    "tasks": {
      "done": 18,
      "total": 18
    },
    "artifacts": {
      "proposal": true,
      "tasks": true
    }
  },
  {
    "name": "2026-06-30-page-003",
    "date": "2026-06-30",
    "summary": "The Product Overview page is the main platform exploration page — a 12-section deep-dive into every module, persona panel, workflow, and security feature of OptiFlow OS. It serves as the primary produ",
    "tasks": {
      "done": 28,
      "total": 28
    },
    "artifacts": {
      "proposal": true,
      "tasks": true
    }
  },
  {
    "name": "2026-06-30-page-004-feature-showcase",
    "date": "2026-06-30",
    "summary": "",
    "tasks": {
      "done": 35,
      "total": 35
    },
    "artifacts": {
      "proposal": true,
      "tasks": true
    }
  },
  {
    "name": "2026-06-30-page-006-pricing",
    "date": "2026-06-30",
    "summary": "",
    "tasks": {
      "done": 0,
      "total": 10
    },
    "artifacts": {
      "proposal": true,
      "tasks": true
    }
  },
  {
    "name": "2026-06-30-page-007-newsletter-content",
    "date": "2026-06-30",
    "summary": "",
    "tasks": {
      "done": 8,
      "total": 8
    },
    "artifacts": {
      "proposal": true,
      "tasks": true
    }
  },
  {
    "name": "2026-06-30-site-nav-structure",
    "date": "2026-06-30",
    "summary": "",
    "tasks": {
      "done": 0,
      "total": 0
    },
    "artifacts": {
      "proposal": true,
      "tasks": true
    }
  }
]